limpador/__init__.py
limpador-0.7.0.dist-info/METADATA
limpador-0.7.0.dist-info/WHEEL
limpador-0.7.0.dist-info/top_level.txt
limpador-0.7.0.dist-info/RECORD
