Metadata-Version: 2.4
Name: limpador
Version: 0.7.0
Requires-Python: >=3.10
Requires-Dist: polars>=1.2.0
